MANIFEST.in
README.md
setup.cfg
setup.py
versioneer.py
hdl_checker/__init__.py
hdl_checker/__main__.py
hdl_checker/_version.py
hdl_checker/builder_utils.py
hdl_checker/core.py
hdl_checker/database.py
hdl_checker/diagnostics.py
hdl_checker/exceptions.py
hdl_checker/handlers.py
hdl_checker/lsp.py
hdl_checker/parser_utils.py
hdl_checker/path.py
hdl_checker/serialization.py
hdl_checker/server.py
hdl_checker/static_check.py
hdl_checker/types.py
hdl_checker/utils.py
hdl_checker.egg-info/PKG-INFO
hdl_checker.egg-info/SOURCES.txt
hdl_checker.egg-info/dependency_links.txt
hdl_checker.egg-info/entry_points.txt
hdl_checker.egg-info/requires.txt
hdl_checker.egg-info/top_level.txt
hdl_checker/builders/__init__.py
hdl_checker/builders/base_builder.py
hdl_checker/builders/fallback.py
hdl_checker/builders/ghdl.py
hdl_checker/builders/msim.py
hdl_checker/builders/xvhdl.py
hdl_checker/config_generators/__init__.py
hdl_checker/config_generators/base_generator.py
hdl_checker/config_generators/simple_finder.py
hdl_checker/parsers/__init__.py
hdl_checker/parsers/base_parser.py
hdl_checker/parsers/config_parser.py
hdl_checker/parsers/verilog_parser.py
hdl_checker/parsers/vhdl_parser.py
hdl_checker/parsers/elements/__init__.py
hdl_checker/parsers/elements/dependency_spec.py
hdl_checker/parsers/elements/design_unit.py
hdl_checker/parsers/elements/identifier.py
hdl_checker/parsers/elements/parsed_element.py
hdl_checker/tests/__init__.py
hdl_checker/tests/test_base_server.py
hdl_checker/tests/test_builder_utils.py
hdl_checker/tests/test_builders.py
hdl_checker/tests/test_config_generator.py
hdl_checker/tests/test_config_parser.py
hdl_checker/tests/test_database.py
hdl_checker/tests/test_lsp.py
hdl_checker/tests/test_lsp_utils.py
hdl_checker/tests/test_misc.py
hdl_checker/tests/test_parser_utils.py
hdl_checker/tests/test_server.py
hdl_checker/tests/test_server_handlers.py
hdl_checker/tests/test_static_check.py
hdl_checker/tests/test_verilog_parser.py
hdl_checker/tests/test_vhdl_parser.py