Metadata-Version: 2.1
Name: hdl-checker
Version: 0.7.2
Summary: HDL code checker
Home-page: https://github.com/suoto/hdl_checker
Author: Andre Souto
Author-email: andre820@gmail.com
License: GPLv3
Keywords: VHDL Verilog SystemVerilog linter LSP language server protocol vimhdl vim-hdl
Platform: any
Classifier: Development Status :: 5 - Production/Stable
Classifier: Environment :: Console
Classifier: Intended Audience :: Developers
Classifier: License :: OSI Approved :: GNU General Public License v3 (GPLv3)
Classifier: Operating System :: Microsoft :: Windows
Classifier: Operating System :: POSIX :: Linux
Classifier: Programming Language :: Python
Classifier: Programming Language :: Python :: 3
Classifier: Programming Language :: Python :: 3.5
Classifier: Programming Language :: Python :: 3.6
Classifier: Programming Language :: Python :: 3.7
Classifier: Topic :: Software Development
Classifier: Topic :: Scientific/Engineering :: Electronic Design Automation (EDA)
Classifier: Topic :: Text Editors :: Integrated Development Environments (IDE)
